devtrans.py
devtrans-3.0.data/scripts/transliterate
devtrans-3.0.dist-info/LICENSE
devtrans-3.0.dist-info/METADATA
devtrans-3.0.dist-info/WHEEL
devtrans-3.0.dist-info/top_level.txt
devtrans-3.0.dist-info/RECORD
