Metadata-Version: 2.1
Name: devtrans
Version: 3.0
Summary: Convert among Devanagari transliteration systems
Home-page: https://gitlab.com/gaudha/devanagari-transliterators
Author: Sanal Vikram
Author-email: zombiechum@gmail.com
License: MIT
Platform: UNKNOWN
Classifier: Development Status :: 5 - Production/Stable
Classifier: Programming Language :: Python :: 3
Classifier: Operating System :: OS Independent
